sdk_erator/__init__.py
sdk_erator-0.1.0.dist-info/METADATA
sdk_erator-0.1.0.dist-info/WHEEL
sdk_erator-0.1.0.dist-info/RECORD
