Metadata-Version: 2.1
Name: sdk-erator
Version: 0.1.0
Summary: 
Author: Peter
Author-email: peterHoburg@users.noreply.github.com
Requires-Python: >=3.10,<4.0
Classifier: Programming Language :: Python :: 3
Classifier: Programming Language :: Python :: 3.10
Classifier: Programming Language :: Python :: 3.11
Requires-Dist: pydantic (>=2.3.0,<3.0.0)
